[
  {
    "displayName": "网易云阅读",
    "description": "100000+好书杂志免费读",
    "lIconUrl": "yuedu.jpg",
    "hIconUrl": "yuedu.jpg",
    "downloadUrl": "http://163.fm/ZSQDg1D",
    "schema": null
  },
  {
    "displayName": "网易新闻",
    "description": "新闻海量实时 跟贴犀利精彩",
    "lIconUrl": "xinwen.jpg",
    "hIconUrl": "xinwen.jpg",
    "downloadUrl": "http://itunes.apple.com/cn/app/id425349261?mt=8",
    "schema": "newsapp"
  },
  {
    "displayName": "网易微博",
    "description": "有态度的微博",
    "lIconUrl": "weibo.jpg",
    "hIconUrl": "weibo.jpg",
    "downloadUrl": "http://itunes.apple.com/cn/app/163/id383629309?mt=8",
    "schema": "microblogging"
  },
  {
    "displayName": "有道云笔记",
    "description": "随时随地，记录一切",
    "lIconUrl": "biji.jpg",
    "hIconUrl": "biji.jpg",
    "downloadUrl": "http://itunes.apple.com/cn/app/id450748070?mt=8",
    "schema": "youdaonote"
  },
  {
    "displayName": "有道词典",
    "description": "最好用的免费全能翻译软件",
    "lIconUrl": "cidian.jpg",
    "hIconUrl": "cidian.jpg",
    "downloadUrl": "http://itunes.apple.com/cn/app/id353115739?mt=8",
    "schema": "yddictProapp"
  }
]